humanitix_client/__init__.py
humanitix_client/api/__init__.py
humanitix_client/api/events/__init__.py
humanitix_client/api/events/get_v1_events.py
humanitix_client/api/events/get_v_1_events_event_id.py
humanitix_client/api/events/get_v_1_events_event_id_check_in_count.py
humanitix_client/api/events/patch_v_1_events_event_id.py
humanitix_client/api/events/post_v1_events.py
humanitix_client/api/global_/__init__.py
humanitix_client/api/global_/get_v1_global_events.py
humanitix_client/api/orders/__init__.py
humanitix_client/api/orders/get_v_1_events_event_id_orders.py
humanitix_client/api/orders/get_v_1_events_event_id_orders_order_id.py
humanitix_client/api/tags/__init__.py
humanitix_client/api/tags/get_v1_tags.py
humanitix_client/api/tags/get_v_1_tags_tag_id.py
humanitix_client/api/tickets/__init__.py
humanitix_client/api/tickets/get_v_1_events_event_id_tickets.py
humanitix_client/api/tickets/get_v_1_events_event_id_tickets_ticket_id.py
humanitix_client/api/tickets/post_v_1_events_event_id_tickets_ticket_id_check_in.py
humanitix_client/api/tickets/post_v_1_events_event_id_tickets_ticket_id_check_out.py
humanitix_client/api/tickets/post_v_1_events_event_id_tickets_ticket_id_transfer.py
humanitix_client/client.py
humanitix_client/errors.py
humanitix_client/models/__init__.py
humanitix_client/models/accessibility.py
humanitix_client/models/accessibility_feature.py
humanitix_client/models/additional_fields.py
humanitix_client/models/additional_fields_details.py
humanitix_client/models/additional_questions.py
humanitix_client/models/additional_questions_input_type.py
humanitix_client/models/artist.py
humanitix_client/models/bad_request_error.py
humanitix_client/models/category.py
humanitix_client/models/category_auto_boat_and_air.py
humanitix_client/models/category_auto_boat_and_air_category.py
humanitix_client/models/category_auto_boat_and_air_subcategory.py
humanitix_client/models/category_business_and_professional.py
humanitix_client-1.18.0.4.dist-info/METADATA
humanitix_client-1.18.0.4.dist-info/WHEEL
humanitix_client-1.18.0.4.dist-info/RECORD
